perovskite_iemap.py
perovskite_iemap-0.1.1.dist-info/METADATA
perovskite_iemap-0.1.1.dist-info/WHEEL
perovskite_iemap-0.1.1.dist-info/RECORD
