Metadata-Version: 2.1
Name: perovskite-iemap
Version: 0.1.1
Summary: 
Author: SergioEanX
Author-email: sergio.ferlito@enea.it
Requires-Python: >=3.10,<4.0
Classifier: Programming Language :: Python :: 3
Classifier: Programming Language :: Python :: 3.10
Classifier: Programming Language :: Python :: 3.11
Classifier: Programming Language :: Python :: 3.12
